LICENSE
mltraq/__init__.py
mltraq/cli.py
mltraq/experiment.py
mltraq/job.py
mltraq/opts.py
mltraq/run.py
mltraq/runs.py
mltraq/session.py
mltraq/steps/__init__.py
mltraq/steps/chdir.py
mltraq/steps/codelog.py
mltraq/steps/drop_fields.py
mltraq/steps/init_fields.py
mltraq/steps/init_sequences.py
mltraq/steps/nothing.py
mltraq/steps/sleep.py
mltraq/storage/__init__.py
mltraq/storage/archivestore.py
mltraq/storage/database.py
mltraq/storage/datastore.py
mltraq/storage/datastream.py
mltraq/storage/models.py
mltraq/storage/serialization.py
mltraq/storage/serializers/__init__.py
mltraq/storage/serializers/datapak.py
mltraq/storage/serializers/pickle.py
mltraq/storage/serializers/pickle_opcodes_whitelist.py
mltraq/storage/serializers/serializer.py
mltraq/utils/__init__.py
mltraq/utils/base_options.py
mltraq/utils/bunch.py
mltraq/utils/enums.py
mltraq/utils/exceptions.py
mltraq/utils/frames.py
mltraq/utils/fs.py
mltraq/utils/json.py
mltraq/utils/logging.py
mltraq/utils/reproducibility.py
mltraq/utils/sequence.py
mltraq/utils/sysenv.py
mltraq/utils/sysmon.py
mltraq/utils/text.py
mltraq/utils/web.py
mltraq/version.py
mltraq-0.1.165.dist-info/entry_points.txt
mltraq-0.1.165.dist-info/LICENSE
mltraq-0.1.165.dist-info/WHEEL
mltraq-0.1.165.dist-info/METADATA
mltraq-0.1.165.dist-info/RECORD
