Metadata-Version: 2.1
Name: mltraq
Version: 0.1.165
Summary: Track and Collaborate on ML & AI Experiments.
Home-page: https://mltraq.com/
License: BSD-3
Author: Michele Dallachiesa
Author-email: michele.dallachiesa@sigforge.com
Requires-Python: >=3.9.0
Classifier: Development Status :: 3 - Alpha
Classifier: Intended Audience :: Science/Research
Classifier: License :: OSI Approved
Classifier: License :: Other/Proprietary License
Classifier: Programming Language :: Python :: 3
Classifier: Programming Language :: Python :: 3.9
Classifier: Programming Language :: Python :: 3.10
Classifier: Programming Language :: Python :: 3.11
Requires-Dist: cloudpickle (>=2.2.0)
Requires-Dist: joblib (>=1.4.0)
Requires-Dist: pandas (>=1.5.3)
Requires-Dist: pyarrow (>=10.0.0)
Requires-Dist: requests (>=2.32.3,<3.0.0)
Requires-Dist: sqlalchemy (>=2.0.0)
Requires-Dist: tabulate (>=0.9.0)
Requires-Dist: tqdm (>=4.64.1)
Project-URL: Repository, https://github.com/elehcimd/mltraq
